{
  "@context": "http://iiif.io/api/presentation/2/context.json",
  "@id": "http://iiif.nli.org.il/IIIFv21/DOCID/NNL_ARCHIVE_AL004023359/manifest",
  "@type": "sc:Manifest",
  "attribution": [
    "הספרייה הלאומית, מארכיון דן הדני. יוצר/ים: [יש לציין את שם היוצר/ים]. אם שם היוצר/ים אינו ידוע יש לציין: יוצר/ים: צוות יפפא The National Library of Israel, from Dan Hadani's Archive. Photographer: [Photographer's Name] If the photographer's name is not known please indicate IPPA Staff as the Photographer"
  ],
  "logo": [
    "http://iiif.nli.org.il/IIIFv21/images/nli_logo.jpg"
  ],
  "license": [
    "http://web.nli.org.il/sites/NLI/Hebrew/library/items-terms-of-use/Pages/nli-fair-use.aspx"
  ],
  "description": "Tel Aviv-Yafo (Israel) -- Photographs",
  "label": "הפרדת דת ומדינה.",
  "metadata": [
    {
      "label": "Title",
      "value": "הפרדת דת ומדינה."
    },
    {
      "label": "Base",
      "value": "NNL01"
    },
    {
      "label": "Subject",
      "value": "Tel Aviv-Yafo (Israel) -- Photographs"
    },
    {
      "label": "Source",
      "value": "The National Library of Israel"
    },
    {
      "label": "The Creator",
      "value": "Michael Meiers photographer"
    },
    {
      "label": "Doc Id",
      "value": "NNL_ARCHIVE_AL004023359"
    },
    {
      "label": "Type",
      "value": "image"
    },
    {
      "label": "Format",
      "value": "1 photograph : b/w ; 35 mm.."
    },
    {
      "label": "Alternative Title",
      "value": "Separate the Religion and State."
    },
    {
      "label": "SysNum",
      "value": "004023359"
    }
  ],
  "sequences": [
    {
      "@id": "http://iiif.nli.org.il/IIIFv21/NNL_ARCHIVE_AL004023359/sequence/IE45826270",
      "@type": "sc:Sequence",
      "label": "הפרדת דת ומדינה.",
      "canvases": [
        {
          "@id": "http://iiif.nli.org.il/IIIFv21/FL45826285",
          "@type": "sc:Canvas",
          "label": "הפרדת דת ומדינה.",
          "width": 3320,
          "height": 2080,
          "images": [
            {
              "@id": "FL45826285",
              "@type": "oa:Annotation",
              "motivation": "sc:painting",
              "on": "http://iiif.nli.org.il/IIIFv21/FL45826285",
              "resource": {
                "@id": "http://iiif.nli.org.il/IIIFv21/FL45826285/full/max/0/default.jpg",
                "@type": "dctypes:Image",
                "label": "הפרדת דת ומדינה.",
                "format": "image/jpeg;",
                "service": {
                  "@context": "http://iiif.io/api/image/2/context.json",
                  "@id": "http://iiif.nli.org.il/IIIFv21/FL45826285",
                  "label": "הפרדת דת ומדינה.",
                  "profile": "http://iiif.io/api/image/2/level1.json"
                },
                "height": 2080,
                "width": 3320
              }
            }
          ]
        }
      ]
    }
  ],
  "structures": [
    {
      "@id": "REP45826284",
      "@type": "sc:Range",
      "label": "REP45826284",
      "members": [
        {
          "@id": "http://iiif.nli.org.il/IIIFv21/FL45826285",
          "@type": "sc:Canvas",
          "label": "הפרדת דת ומדינה."
        }
      ]
    }
  ],
  "related": "http://merhav.nli.org.il/primo_library/libweb/action/display.do?tabs=detailsTab&ct=display&fn=search&doc=NNL_ARCHIVE_AL004023359",
  "viewingHint": "paged"
}