{
  "@context": "http://iiif.io/api/presentation/2/context.json",
  "@id": "http://iiif.nli.org.il/IIIFv21/DOCID/NNL_ARCHIVE_AL004039053/manifest",
  "@type": "sc:Manifest",
  "attribution": [
    "הספרייה הלאומית, מארכיון דן הדני. יוצר/ים: [יש לציין את שם היוצר/ים]. אם שם היוצר/ים אינו ידוע יש לציין: יוצר/ים: צוות יפפא The National Library of Israel, from Dan Hadani's Archive. Photographer: [Photographer's Name] If the photographer's name is not known please indicate IPPA Staff as the Photographer"
  ],
  "logo": [
    "http://iiif.nli.org.il/IIIFv21/images/nli_logo.jpg"
  ],
  "license": [
    "http://web.nli.org.il/sites/NLI/Hebrew/library/items-terms-of-use/Pages/nli-fair-use.aspx"
  ],
  "description": "ʻAbbās, Maḥmūd, 1935- -- Photographs",
  "label": "During the visit of the PLO Leader with Israel President Ezer Weizman, some other discussins were held by lower officials from both sides.",
  "metadata": [
    {
      "label": "Title",
      "value": "During the visit of the PLO Leader with Israel President Ezer Weizman, some other discussins were held by lower officials from both sides."
    },
    {
      "label": "Base",
      "value": "NNL01"
    },
    {
      "label": "Subject",
      "value": "ʻAbbās, Maḥmūd, 1935- -- Photographs"
    },
    {
      "label": "Source",
      "value": "The National Library of Israel"
    },
    {
      "label": "The Creator",
      "value": "Gideon Markowiz photographer"
    },
    {
      "label": "Doc Id",
      "value": "NNL_ARCHIVE_AL004039053"
    },
    {
      "label": "Type",
      "value": "image"
    },
    {
      "label": "Format",
      "value": "1 photograph : color ; 35 mm.."
    },
    {
      "label": "SysNum",
      "value": "004039053"
    }
  ],
  "sequences": [
    {
      "@id": "http://iiif.nli.org.il/IIIFv21/NNL_ARCHIVE_AL004039053/sequence/IE45751671",
      "@type": "sc:Sequence",
      "label": "During the visit of the PLO Leader with Israel President Ezer Weizman  some other discussins were held by lower officials from both sides.",
      "canvases": [
        {
          "@id": "http://iiif.nli.org.il/IIIFv21/FL45751695",
          "@type": "sc:Canvas",
          "label": "During the visit of the PLO Leader with Israel President Ezer Weizman  some other discussins were held by lower officials from both sides.",
          "width": 1179,
          "height": 1807,
          "images": [
            {
              "@id": "FL45751695",
              "@type": "oa:Annotation",
              "motivation": "sc:painting",
              "on": "http://iiif.nli.org.il/IIIFv21/FL45751695",
              "resource": {
                "@id": "http://iiif.nli.org.il/IIIFv21/FL45751695/full/max/0/default.jpg",
                "@type": "dctypes:Image",
                "label": "During the visit of the PLO Leader with Israel President Ezer Weizman  some other discussins were held by lower officials from both sides.",
                "format": "image/jpeg;",
                "service": {
                  "@context": "http://iiif.io/api/image/2/context.json",
                  "@id": "http://iiif.nli.org.il/IIIFv21/FL45751695",
                  "label": "During the visit of the PLO Leader with Israel President Ezer Weizman  some other discussins were held by lower officials from both sides.",
                  "profile": "http://iiif.io/api/image/2/level1.json"
                },
                "height": 1807,
                "width": 1179
              }
            }
          ]
        }
      ]
    }
  ],
  "structures": [
    {
      "@id": "REP45751692",
      "@type": "sc:Range",
      "label": "REP45751692",
      "members": [
        {
          "@id": "http://iiif.nli.org.il/IIIFv21/FL45751695",
          "@type": "sc:Canvas",
          "label": "During the visit of the PLO Leader with Israel President Ezer Weizman  some other discussins were held by lower officials from both sides."
        }
      ]
    }
  ],
  "related": "http://merhav.nli.org.il/primo_library/libweb/action/display.do?tabs=detailsTab&ct=display&fn=search&doc=NNL_ARCHIVE_AL004039053",
  "viewingHint": "paged"
}