{
  "@context": "http://iiif.io/api/presentation/2/context.json",
  "@id": "http://iiif.nli.org.il/IIIFv21/DOCID/NNL_Ephemera700262010/manifest",
  "@type": "sc:Manifest",
  "logo": [
    "http://iiif.nli.org.il/IIIFv21/images/nli_logo.jpg"
  ],
  "description": "מ. אלקץ; בחירות; יהודים וערבים; פוליטיקה; סוציאליזם",
  "label": "לכל פועלי חדרה!",
  "metadata": [
    {
      "label": "Title",
      "value": "לכל פועלי חדרה!"
    },
    {
      "label": "Publisher",
      "value": "מפלגת פועלי ארץ ישראל (פועלי ציון)"
    },
    {
      "label": "Base",
      "value": "NNL03"
    },
    {
      "label": "Subject",
      "value": "מ. אלקץ; בחירות; יהודים וערבים; פוליטיקה; סוציאליזם"
    },
    {
      "label": "Source",
      "value": "אוסף האפמרה - הספרייה הלאומית"
    },
    {
      "label": "Doc Id",
      "value": "NNL_Ephemera700262010"
    },
    {
      "label": "Creation Date",
      "value": "1932"
    },
    {
      "label": "Type",
      "value": "sheet"
    },
    {
      "label": "Language",
      "value": "heb"
    },
    {
      "label": "SysNum",
      "value": "700262010"
    }
  ],
  "sequences": [
    {
      "@id": "http://iiif.nli.org.il/IIIFv21/NNL_Ephemera700262010/sequence/IE9168710",
      "@type": "sc:Sequence",
      "label": "לכל פועלי חדרה!",
      "canvases": [
        {
          "@id": "http://iiif.nli.org.il/IIIFv21/FL9180311",
          "@type": "sc:Canvas",
          "label": "לכל פועלי חדרה!",
          "width": 800,
          "height": 793,
          "images": [
            {
              "@id": "FL9180311",
              "@type": "oa:Annotation",
              "motivation": "sc:painting",
              "on": "http://iiif.nli.org.il/IIIFv21/FL9180311",
              "resource": {
                "@id": "http://iiif.nli.org.il/IIIFv21/FL9180311/full/max/0/default.jpg",
                "@type": "dctypes:Image",
                "label": "לכל פועלי חדרה!",
                "format": "image/jpeg;",
                "service": {
                  "@context": "http://iiif.io/api/image/2/context.json",
                  "@id": "http://iiif.nli.org.il/IIIFv21/FL9180311",
                  "label": "לכל פועלי חדרה!",
                  "profile": "http://iiif.io/api/image/2/level1.json"
                },
                "height": 793,
                "width": 800
              }
            }
          ]
        }
      ]
    }
  ],
  "structures": [
    {
      "@id": "REP9180310",
      "@type": "sc:Range",
      "label": "REP9180310",
      "members": [
        {
          "@id": "http://iiif.nli.org.il/IIIFv21/FL9180311",
          "@type": "sc:Canvas",
          "label": "לכל פועלי חדרה!"
        }
      ]
    }
  ],
  "related": "http://merhav.nli.org.il/primo_library/libweb/action/display.do?tabs=detailsTab&ct=display&fn=search&doc=NNL_Ephemera700262010",
  "viewingHint": "paged"
}