{
  "@context": "http://iiif.io/api/presentation/2/context.json",
  "@id": "http://iiif.nli.org.il/IIIFv21/DOCID/NNL_MAPS_JER004083902/manifest",
  "@type": "sc:Manifest",
  "attribution": [
    "הספרייה הלאומית, אוסף המפות ע\"ש ערן לאור"
  ],
  "logo": [
    "http://iiif.nli.org.il/IIIFv21/images/nli_logo.jpg"
  ],
  "license": [
    "http://web.nli.org.il/sites/NLI/Hebrew/library/items-terms-of-use/Pages/nli-public-domain.aspx"
  ],
  "description": "Syria -- Maps ; מדריכי פנאי, מדריכי טיולים, ספרי בישול",
  "label": "Hama ouest /;&nbsp;Dressè, heliogravè et publie par le Service Geograhphique de l'Armée.",
  "metadata": [
    {
      "label": "Title",
      "value": "Hama ouest /;&nbsp;Dressè, heliogravè et publie par le Service Geograhphique de l'Armée."
    },
    {
      "label": "Base",
      "value": "NNL01"
    },
    {
      "label": "Subject",
      "value": "Syria -- Maps ; מדריכי פנאי, מדריכי טיולים, ספרי בישול"
    },
    {
      "label": "Source",
      "value": "The National Library of Israel"
    },
    {
      "label": "The Creator",
      "value": "France. Armée. Service géographique"
    },
    {
      "label": "Doc Id",
      "value": "NNL_MAPS_JER004083902"
    },
    {
      "label": "Creation Date",
      "value": "1931"
    },
    {
      "label": "Type",
      "value": "map"
    },
    {
      "label": "Format",
      "value": "1 sheet : color ; 72.3 x 54 cm.."
    },
    {
      "label": "Language",
      "value": "fre"
    },
    {
      "label": "Alternative Title",
      "value": "Levant 1:50,000 ; NI - 37 - 19- 2a"
    },
    {
      "label": "SysNum",
      "value": "004083902"
    }
  ],
  "sequences": [],
  "structures": [],
  "related": "http://merhav.nli.org.il/primo_library/libweb/action/display.do?tabs=detailsTab&ct=display&fn=search&doc=NNL_MAPS_JER004083902",
  "viewingHint": "paged"
}