{
  "@context": "http://iiif.io/api/presentation/2/context.json",
  "@id": "http://iiif.nli.org.il/IIIFv21/DOCID/NNL_MAPS_JER002498331/manifest",
  "@type": "sc:Manifest",
  "attribution": [
    "הספרייה הלאומית, אוסף המפות ע\"ש ערן לאור"
  ],
  "logo": [
    "http://iiif.nli.org.il/IIIFv21/images/nli_logo.jpg"
  ],
  "license": [
    "http://web.nli.org.il/sites/NLI/Hebrew/library/items-terms-of-use/Pages/nli-public-domain.aspx"
  ],
  "description": "Libya -- Maps; Africa, North -- Maps",
  "label": "Ora Maritima et Interna Libyae regio una cum Oasibus et Aegypto :;&nbsp;Accedit peculiaris Oasium ac praesertium Ammonii deliniatio. Nomina sub quibus linea...",
  "metadata": [
    {
      "label": "Title",
      "value": "Ora Maritima et Interna Libyae regio una cum Oasibus et Aegypto :;&nbsp;Accedit peculiaris Oasium ac praesertium Ammonii deliniatio. Nomina sub quibus linea..."
    },
    {
      "label": "Publisher",
      "value": "Hannover :Steind v. J. G. Schwab"
    },
    {
      "label": "Base",
      "value": "NNL01"
    },
    {
      "label": "Subject",
      "value": "Libya -- Maps; Africa, North -- Maps"
    },
    {
      "label": "Source",
      "value": "The National Library of Israel"
    },
    {
      "label": "The Creator",
      "value": "Schwab J. G."
    },
    {
      "label": "Doc Id",
      "value": "NNL_MAPS_JER002498331"
    },
    {
      "label": "Creation Date",
      "value": "1830?"
    },
    {
      "label": "Type",
      "value": "map"
    },
    {
      "label": "Format",
      "value": "1 map ; 30 X 36.5 cm.."
    },
    {
      "label": "Language",
      "value": "lat"
    },
    {
      "label": "SysNum",
      "value": "002498331"
    }
  ],
  "sequences": [
    {
      "@id": "http://iiif.nli.org.il/IIIFv21/NNL_MAPS_JER002498331/sequence/IE13727081",
      "@type": "sc:Sequence",
      "label": "Africa; North",
      "canvases": [
        {
          "@id": "http://iiif.nli.org.il/IIIFv21/FL13737792",
          "@type": "sc:Canvas",
          "label": "Image",
          "width": 6381,
          "height": 5665,
          "images": [
            {
              "@id": "FL13737792",
              "@type": "oa:Annotation",
              "motivation": "sc:painting",
              "on": "http://iiif.nli.org.il/IIIFv21/FL13737792",
              "resource": {
                "@id": "http://iiif.nli.org.il/IIIFv21/FL13737792/full/max/0/default.jpg",
                "@type": "dctypes:Image",
                "label": "Image",
                "format": "image/jpeg;",
                "service": {
                  "@context": "http://iiif.io/api/image/2/context.json",
                  "@id": "http://iiif.nli.org.il/IIIFv21/FL13737792",
                  "label": "Image",
                  "profile": "http://iiif.io/api/image/2/level1.json"
                },
                "height": 5665,
                "width": 6381
              }
            }
          ]
        }
      ]
    }
  ],
  "structures": [
    {
      "@id": "REP13737791",
      "@type": "sc:Range",
      "label": "REP13737791",
      "members": [
        {
          "@id": "http://iiif.nli.org.il/IIIFv21/FL13737792",
          "@type": "sc:Canvas",
          "label": "Image"
        }
      ]
    }
  ],
  "related": "http://merhav.nli.org.il/primo_library/libweb/action/display.do?tabs=detailsTab&ct=display&fn=search&doc=NNL_MAPS_JER002498331",
  "viewingHint": "paged"
}