{
  "@context": "http://iiif.io/api/presentation/2/context.json",
  "@id": "http://iiif.nli.org.il/IIIFv21/DOCID/NNL_Ephemera700111893/manifest",
  "@type": "sc:Manifest",
  "logo": [
    "http://iiif.nli.org.il/IIIFv21/images/nli_logo.jpg"
  ],
  "description": "Music Performance -- Israel; Orchestra -- Israel; Music -- Performance -- Israel; First Battalion Northamptonshire Regiment; מופע מוסיקה; תזמורת; עיריה - עיריות - מוניציפאלי; Urban Ad; תל אביב",
  "label": "הודעה לקהל - התזמרת הצבאית של הגדוד",
  "metadata": [
    {
      "label": "Title",
      "value": "הודעה לקהל - התזמרת הצבאית של הגדוד"
    },
    {
      "label": "Publisher",
      "value": "עירית תל אביב"
    },
    {
      "label": "Base",
      "value": "NNL03"
    },
    {
      "label": "Subject",
      "value": "Music Performance -- Israel; Orchestra -- Israel; Music -- Performance -- Israel; First Battalion Northamptonshire Regiment; מופע מוסיקה; תזמורת; עיריה - עיריות - מוניציפאלי; Urban Ad; תל אביב"
    },
    {
      "label": "Source",
      "value": "Ephemera Collection - The National Library of Israel"
    },
    {
      "label": "Doc Id",
      "value": "NNL_Ephemera700111893"
    },
    {
      "label": "Creation Date",
      "value": "1930"
    },
    {
      "label": "Type",
      "value": "sheet"
    },
    {
      "label": "Language",
      "value": "heb;eng"
    },
    {
      "label": "SysNum",
      "value": "700111893"
    }
  ],
  "sequences": [
    {
      "@id": "http://iiif.nli.org.il/IIIFv21/NNL_Ephemera700111893/sequence/IE5027161",
      "@type": "sc:Sequence",
      "label": "אוסף הספרייה הלאומית",
      "canvases": [
        {
          "@id": "http://iiif.nli.org.il/IIIFv21/FL5394992",
          "@type": "sc:Canvas",
          "label": "אוסף הספרייה הלאומית",
          "width": 599,
          "height": 800,
          "images": [
            {
              "@id": "FL5394992",
              "@type": "oa:Annotation",
              "motivation": "sc:painting",
              "on": "http://iiif.nli.org.il/IIIFv21/FL5394992",
              "resource": {
                "@id": "http://iiif.nli.org.il/IIIFv21/FL5394992/full/max/0/default.jpg",
                "@type": "dctypes:Image",
                "label": "אוסף הספרייה הלאומית",
                "format": "image/jpeg;",
                "service": {
                  "@context": "http://iiif.io/api/image/2/context.json",
                  "@id": "http://iiif.nli.org.il/IIIFv21/FL5394992",
                  "label": "אוסף הספרייה הלאומית",
                  "profile": "http://iiif.io/api/image/2/level1.json"
                },
                "height": 800,
                "width": 599
              }
            }
          ]
        }
      ]
    }
  ],
  "structures": [
    {
      "@id": "REP5394991",
      "@type": "sc:Range",
      "label": "REP5394991",
      "members": [
        {
          "@id": "http://iiif.nli.org.il/IIIFv21/FL5394992",
          "@type": "sc:Canvas",
          "label": "אוסף הספרייה הלאומית"
        }
      ]
    }
  ],
  "related": "http://merhav.nli.org.il/primo_library/libweb/action/display.do?tabs=detailsTab&ct=display&fn=search&doc=NNL_Ephemera700111893",
  "viewingHint": "paged"
}